eat/__init__.py
eat/eatme.py
eat-1.0.0.dist-info/licenses/LICENSE
eat-1.0.0.dist-info/WHEEL
eat-1.0.0.dist-info/METADATA
eat-1.0.0.dist-info/RECORD
