Metadata-Version: 2.4
Name: eat
Version: 1.0.0
Summary: A funny execute module, enjoy.
Author-email: AYMEN||d9c <aymenmw@proton.me>
License-Expression: GPL-3.0-or-later
License-File: LICENSE
Project-URL: Home, https://github.com/kkkik/eat
